op_verification/__init__.py
op_verification/reference_data.py
op_verification/verification_data.py
op_verification/verify.py
op_verification/data/county_shapefiles/2013-HD-ProclamationPlan/2013ProclamationPlan.dbf
op_verification/data/county_shapefiles/2013-HD-ProclamationPlan/2013ProclamationPlan.prj
op_verification/data/county_shapefiles/2013-HD-ProclamationPlan/2013ProclamationPlan.sbn
op_verification/data/county_shapefiles/2013-HD-ProclamationPlan/2013ProclamationPlan.sbx
op_verification/data/county_shapefiles/2013-HD-ProclamationPlan/2013ProclamationPlan.shp
op_verification/data/county_shapefiles/2013-HD-ProclamationPlan/2013ProclamationPlan.shx
op_verification/data/county_shapefiles/2013-HD-ProclamationPlan/source.txt
op_verification/data/county_shapefiles/cb_2016_us_county_500k/cb_2016_us_county_500k.cpg
op_verification/data/county_shapefiles/cb_2016_us_county_500k/cb_2016_us_county_500k.dbf
op_verification/data/county_shapefiles/cb_2016_us_county_500k/cb_2016_us_county_500k.prj
op_verification/data/county_shapefiles/cb_2016_us_county_500k/cb_2016_us_county_500k.shp
op_verification/data/county_shapefiles/cb_2016_us_county_500k/cb_2016_us_county_500k.shp.ea.iso.xml
op_verification/data/county_shapefiles/cb_2016_us_county_500k/cb_2016_us_county_500k.shp.iso.xml
op_verification/data/county_shapefiles/cb_2016_us_county_500k/cb_2016_us_county_500k.shp.xml
op_verification/data/county_shapefiles/cb_2016_us_county_500k/cb_2016_us_county_500k.shx
op_verification/data/county_shapefiles/cb_2016_us_county_500k/source.txt
op_verification/data/election_results/countypres_2000-2016.csv
op_verification-0.0.10.dist-info/LICENSE
op_verification-0.0.10.dist-info/METADATA
op_verification-0.0.10.dist-info/WHEEL
op_verification-0.0.10.dist-info/top_level.txt
op_verification-0.0.10.dist-info/RECORD
