Metadata-Version: 2.1
Name: op_verification
Version: 0.0.10
Summary: Compares a Precinct-Level Election Shapefile with expected election results and geometries.
Home-page: https://github.com/OpenPrecincts/verification
Author: Baxter Demers
Author-email: baxter.demers@gmail.com
License: UNKNOWN
Platform: UNKNOWN
Classifier: Programming Language :: Python :: 3
Classifier: License :: OSI Approved :: MIT License
Classifier: Operating System :: OS Independent
Requires-Python: >=3.7
